friendli/__init__.py
friendli/config.py
friendli/container/__init__.py
friendli/container/audio.py
friendli/container/chat.py
friendli/container/completions.py
friendli/container/image.py
friendli/container/token.py
friendli/core/__init__.py
friendli/core/_hooks/__init__.py
friendli/core/_hooks/registration.py
friendli/core/_hooks/sdkhooks.py
friendli/core/_hooks/types.py
friendli/core/_version.py
friendli/core/audio.py
friendli/core/basesdk.py
friendli/core/container.py
friendli/core/container_audio.py
friendli/core/container_chat.py
friendli/core/container_completions.py
friendli/core/container_image.py
friendli/core/container_token.py
friendli/core/dataset.py
friendli/core/dedicated.py
friendli/core/dedicated_audio.py
friendli/core/dedicated_chat.py
friendli/core/dedicated_chatrender.py
friendli/core/dedicated_completions.py
friendli/core/dedicated_image.py
friendli/core/dedicated_token.py
friendli/core/embeddings.py
friendli/core/endpoint.py
friendli/core/file_sdk.py
friendli/core/httpclient.py
friendli/core/knowledge.py
friendli/core/model.py
friendli/core/models/__init__.py
friendli/core/models/acceleratorrequirement.py
friendli/core/models/accountfilestatus.py
friendli/core/models/add_samplesop.py
friendli/core/models/addsamplesresponse.py
friendli/core/models/assistantmessage.py
friendli/core/models/assistantmessagetoolcall.py
friendli/core/models/assistantmessagetoolcallfunction.py
friendli/core/models/audiocontent.py
friendli/core/models/audiodata.py
friendli/core/models/audiotranscriptioninputtokendetails.py
friendli/core/models/audiotranscriptionusage.py
friendli/core/models/autoscalingpolicy.py
friendli/core/models/b64imageitem.py
friendli/core/models/body_upload_raw_samples.py
friendli/core/models/chatchoice.py
friendli/core/models/chatchoicemessage.py
friendli/core/models/chatcompletebodytoolchoice.py
friendli/core/models/chatcompletebodytoolchoicefunction.py
friendli/core/models/chatlogprobs.py
friendli/core/models/chatlogprobscontent.py
friendli-0.12.4.dist-info/WHEEL
friendli-0.12.4.dist-info/METADATA
friendli-0.12.4.dist-info/RECORD
