Metadata-Version: 2.3
Name: friendli
Version: 0.12.4
Summary: Python Client SDK Generated by Speakeasy.
Author: FriendliAI Engineering
Author-email: FriendliAI Engineering <eng@friendli.ai>
License: Copyright (c) 2025-present, FriendliAI Inc. All rights reserved.
Requires-Dist: httpcore>=1.0.9
Requires-Dist: httpx>=0.28.1
Requires-Dist: pydantic>=2.11.2
Requires-Python: >=3.9.2
Project-URL: repository, https://github.com/friendliai/friendli-python.git
